iterx_utils/__init__.py
iterx_utils/config.py
iterx_utils/get_throughput.py
iterx_utils/metrics.py
iterx_utils/objectives.py
iterx_utils/quant_utils.py
iterx_utils/utility.py
iterx_utils/utility_tf.py
iterx_utils/utils.py
new_modeling-0.1.0.dist-info/METADATA
new_modeling-0.1.0.dist-info/WHEEL
new_modeling-0.1.0.dist-info/top_level.txt
new_modeling-0.1.0.dist-info/RECORD
