Metadata-Version: 2.1
Name: new_modeling
Version: 0.1.0
Summary: A new package that combines an existing library with new code
Author: valencia
Author-email: valencia.xu@intel.com
Classifier: Programming Language :: Python :: 3
Classifier: License :: OSI Approved :: MIT License
Classifier: Operating System :: OS Independent
Requires-Python: >=3.6
